autoreduce_run_detection/__init__.py
autoreduce_run_detection/run_detection.py
autoreduce_run_detection/settings.py
autoreduce_run_detection/tests/__init__.py
autoreduce_run_detection/tests/test_run_detection.py
autoreduce_run_detection-22.0.0.dev7.dist-info/DESCRIPTION.rst
autoreduce_run_detection-22.0.0.dev7.dist-info/METADATA
autoreduce_run_detection-22.0.0.dev7.dist-info/RECORD
autoreduce_run_detection-22.0.0.dev7.dist-info/WHEEL
autoreduce_run_detection-22.0.0.dev7.dist-info/entry_points.txt
autoreduce_run_detection-22.0.0.dev7.dist-info/metadata.json
autoreduce_run_detection-22.0.0.dev7.dist-info/top_level.txt
