Metadata-Version: 2.0
Name: autoreduce-run-detection
Version: 22.0.0.dev7
Summary: A service to discover and ingest new files produced by the ISIS neutron and muon facility
Home-page: https://github.com/ISISScientificComputing/autoreduce-run-detection
Author: ISIS Autoreduction Team
Author-email: UNKNOWN
License: UNKNOWN
Platform: UNKNOWN
Classifier: Programming Language :: Python :: 3 :: Only
Requires-Dist: autoreduce-utils (>=22.0.0.dev7)
Requires-Dist: filelock
Requires-Dist: requests
